hpctainers/__init__.py
hpctainers/cli.py
hpctainers/api/__init__.py
hpctainers/api/builder.py
hpctainers/api/container.py
hpctainers/api/dag.py
hpctainers/api/decorators.py
hpctainers/api/types.py
hpctainers/api/visualization.py
hpctainers/api/yaml_bridge.py
hpctainers/data/basic/com-openfoam.def
hpctainers/data/basic/foam-extend.def
hpctainers/data/basic/hpctoolkit.def
hpctainers/data/basic/lammps.def
hpctainers/data/basic/openmpi.def
hpctainers/data/basic/org-openfoam.def
hpctainers/lib/__init__.py
hpctainers/lib/build_matrix.py
hpctainers/lib/cache.py
hpctainers/lib/config_parser.py
hpctainers/lib/container_builder.py
hpctainers/lib/dependency_graph.py
hpctainers/lib/external_defs.py
hpctainers/lib/framework_discovery.py
hpctainers/lib/mpi_testing.py
hpctainers/lib/package_data.py
hpctainers/lib/parallel.py
hpctainers/lib/registry.py
hpctainers/lib/reporting.py
hpctainers/lib/security_scanning.py
hpctainers/lib/size_analysis.py
hpctainers/lib/testing.py
hpctainers/shell/__init__.py
hpctainers/shell/builtins.py
hpctainers/shell/interpreter.py
hpctainers/shell/parser.py
hpctainers/shell/repl.py
hpctainers-2.0.1.dist-info/METADATA
hpctainers-2.0.1.dist-info/WHEEL
hpctainers-2.0.1.dist-info/entry_points.txt
hpctainers-2.0.1.dist-info/licenses/LICENSE
hpctainers-2.0.1.dist-info/RECORD
