Metadata-Version: 2.4
Name: hpctainers
Version: 2.0.1
Summary: HPC Container Build System for Apptainer with OpenFOAM, MPI, and scientific computing focus
Author: Mohammed Elwardi Fadeli
License: MIT
License-File: LICENSE
Keywords: apptainer,containers,hpc,mpi,openfoam,scientific-computing,singularity
Classifier: Development Status :: 5 - Production/Stable
Classifier: Intended Audience :: Science/Research
Classifier: License :: OSI Approved :: MIT License
Classifier: Operating System :: POSIX :: Linux
Classifier: Programming Language :: Python :: 3
Classifier: Programming Language :: Python :: 3.12
Classifier: Topic :: Scientific/Engineering
Requires-Python: >=3.10
Requires-Dist: pydantic>=2.0
Requires-Dist: pyyaml>=6.0
Provides-Extra: dev
Requires-Dist: black>=23.0; extra == 'dev'
Requires-Dist: pytest>=7.0; extra == 'dev'
Requires-Dist: ruff>=0.1.0; extra == 'dev'
